pgengine/__init__.py
pgengine/engine.py
pgengine/matrix.py
Pigeon_Game_Engine-1.1.dist-info/METADATA
Pigeon_Game_Engine-1.1.dist-info/WHEEL
Pigeon_Game_Engine-1.1.dist-info/top_level.txt
Pigeon_Game_Engine-1.1.dist-info/RECORD
